LICENSE
MANIFEST.in
README.rst
requirements.txt
rollbar-udp-agent
rollbar-udp-agent.conf
setup.py
rollbar_udp_agent/__init__.py
rollbar_udp_agent/daemon.py
rollbar_udp_agent/rollbar_udp_agent.py
rollbar_udp_agent/util.py
rollbar_udp_agent.egg-info/PKG-INFO
rollbar_udp_agent.egg-info/SOURCES.txt
rollbar_udp_agent.egg-info/dependency_links.txt
rollbar_udp_agent.egg-info/entry_points.txt
rollbar_udp_agent.egg-info/requires.txt
rollbar_udp_agent.egg-info/top_level.txt